MANIFEST.in
setup.py
grr_response_client/__init__.py
grr_response_client/actions.py
grr_response_client/client.py
grr_response_client/client_logging.py
grr_response_client/client_main.py
grr_response_client/client_plugins.py
grr_response_client/client_startup.py
grr_response_client/client_test.py
grr_response_client/client_utils.py
grr_response_client/client_utils_common.py
grr_response_client/client_utils_linux.py
grr_response_client/client_utils_osx.py
grr_response_client/client_utils_osx_linux.py
grr_response_client/client_utils_test.py
grr_response_client/client_utils_windows.py
grr_response_client/client_vfs_test.py
grr_response_client/comms.py
grr_response_client/comms_test.py
grr_response_client/distro_entry.py
grr_response_client/fleetspeak_client.py
grr_response_client/fleetspeak_client_test.py
grr_response_client/fleetspeak_client_wrapper.py
grr_response_client/gcs.py
grr_response_client/gcs_test.py
grr_response_client/grr_fs_client.py
grr_response_client/installer.py
grr_response_client/process_error.py
grr_response_client/streaming.py
grr_response_client/streaming_test.py
grr_response_client/time.py
grr_response_client/time_test.py
grr_response_client/vfs.py
grr_response_client/vfs_test.py
grr_response_client.egg-info/PKG-INFO
grr_response_client.egg-info/SOURCES.txt
grr_response_client.egg-info/dependency_links.txt
grr_response_client.egg-info/entry_points.txt
grr_response_client.egg-info/requires.txt
grr_response_client.egg-info/top_level.txt
grr_response_client/client_actions/__init__.py
grr_response_client/client_actions/action_test.py
grr_response_client/client_actions/admin.py
grr_response_client/client_actions/admin_test.py
grr_response_client/client_actions/cloud.py
grr_response_client/client_actions/cloud_test.py
grr_response_client/client_actions/containers.py
grr_response_client/client_actions/containers_test.py
grr_response_client/client_actions/dummy.py
grr_response_client/client_actions/dummy_test.py
grr_response_client/client_actions/file_finder.py
grr_response_client/client_actions/file_finder_test.py
grr_response_client/client_actions/file_fingerprint.py
grr_response_client/client_actions/file_fingerprint_test.py
grr_response_client/client_actions/large_file.py
