Metadata-Version: 2.4
Name: grr-response-client
Version: 4.0.0.post0
Summary: The GRR Rapid Response client.
Home-page: https://github.com/google/grr
Maintainer: GRR Development Team
Maintainer-email: grr-dev@googlegroups.com
License: Apache License, Version 2.0
Requires-Python: >=3.9
Requires-Dist: absl-py==1.4.0
Requires-Dist: grr-response-core==4.0.0post0
Requires-Dist: pytsk3==20230125
Requires-Dist: libfsntfs-python==20230606
Requires-Dist: fleetspeak-client-bin==0.1.13
Requires-Dist: xattr==0.9.7
Requires-Dist: WMI==1.5.1; sys_platform == "win32"
Requires-Dist: pywin32==303; sys_platform == "win32"
Dynamic: home-page
Dynamic: license
Dynamic: maintainer
Dynamic: maintainer-email
Dynamic: provides-extra
Dynamic: requires-dist
Dynamic: requires-python
Dynamic: summary
